{
    "b77bd052-8319-4780-9170-1546cb8baf33": {
        "image": "https://cdn.staticaly.com/gh/DaiwuShen/daiwuImageBed@main/webP/informatrixspace-informatrix-7.6sblxdx8qhkw.webp",
        "author": "DaiwuShen",
        "date": "2023-03-12",
        "classification": {
            "计算机": "C++"
        },
        "tag": [
            "C++",
            "文件流",
            "变长数组"
        ],
        "path": "static/data/markdown/[C++]狗屁不通文章生成器.md"
    },
    "b4eb9843-5956-4f44-8bfc-2c3b535727e7": {
        "image": "https://cdn.staticaly.com/gh/DaiwuShen/daiwuImageBed@main/webP/informatrixspace-informatrix-12.2jj0koti3ry8.webp",
        "author": "DaiwuShen",
        "date": "2023-03-06",
        "classification": {
            "其他": "日志"
        },
        "tag": [
            "静态网页",
            "日志",
            "Javascript"
        ],
        "path": "static/data/markdown/开发日志2023-03-06.md"
    },
    "9273efb5-2242-489f-9881-00560c864e2a": {
        "image": "https://cdn.staticaly.com/gh/DaiwuShen/daiwuImageBed@main/webP/informatrixspace-informatrix-15.580c0hof04jk.webp",
        "author": "DaiwuShen",
        "date": "2023-03-02",
        "classification": {
            "其他": "日志"
        },
        "tag": [
            "静态网页",
            "日志"
        ],
        "path": "static/data/markdown/开发日志2023-03-02.md"
    },
    "5472e6bc-d42b-49e2-b180-2b48f6fc4e5f": {
        "image": "https://cdn.staticaly.com/gh/DaiwuShen/daiwuImageBed@main/webP/informatrixspace-informatrix-3.4sb5etpj32f4.webp",
        "author": "DaiwuShen",
        "date": "2023-03-01",
        "classification": {
            "其他": "日志"
        },
        "tag": [
            "静态网页",
            "日志"
        ],
        "path": "static/data/markdown/开发日志2023-03-01.md"
    },
    "30d93957-4032-4996-b979-4d60f15d1813": {
        "author": "DaiwuShen",
        "date": "2021-04-14",
        "classification": {
            "计算机": "单片机"
        },
        "tag": [
            "单片机",
            "C语言",
            "80C51"
        ],
        "image": "https://cdn.staticaly.com/gh/DaiwuShen/daiwuImageBed@main/webP/informatrixspace-informatrix-16.27y0r3eip9mo.webp",
        "path": "static/data/html/【51单片机】矩阵键盘逐行扫描法仿真实验+超详细Proteus仿真和Keil操作步骤.html"
    }
}